Metadata-Version: 2.1
Name: django-background-tasks
Version: 1.2.8
Summary: Database backed asynchronous task queue
Home-page: https://github.com/django-background-tasks/django-background-tasks
Author: arteria GmbH, John Montgomery, Alberto Petrucci, Jon Miller
Author-email: iamjonamiller@gmail.com
License: BSD
Classifier: Development Status :: 5 - Production/Stable
Classifier: Environment :: Web Environment
Classifier: Intended Audience :: Developers
Classifier: License :: OSI Approved :: BSD License
Classifier: Operating System :: OS Independent
Classifier: Topic :: Software Development :: Libraries :: Python Modules
Classifier: Framework :: Django
Classifier: Framework :: Django :: 3.0
Classifier: Framework :: Django :: 4.0
Classifier: Framework :: Django :: 5.0
Classifier: Programming Language :: Python :: 3.8
Classifier: Programming Language :: Python :: 3.9
Classifier: Programming Language :: Python :: 3.10
Classifier: Programming Language :: Python :: 3.11
Classifier: Programming Language :: Python :: 3.12
License-File: LICENSE
License-File: AUTHORS.txt
Requires-Dist: six
Requires-Dist: Django>=4.0
